{
  "sections": {
    "a548e521-6c2b-4bbc-aa50-22d5639f23c8": {
      "type": "rich-text",
      "blocks": {
        "template--17158705250556__a548e521-6c2b-4bbc-aa50-22d5639f23c8-heading-1": {
          "type": "heading",
          "settings": {
            "heading": "Talk about your brand",
            "heading_size": "h1"
          }
        },
        "template--17158705250556__a548e521-6c2b-4bbc-aa50-22d5639f23c8-text-1": {
          "type": "text",
          "settings": {
            "text": "<p>Share information about your brand with your customers. Describe a product, make announcements, or welcome customers to your store.<\/p>"
          }
        },
        "template--17158705250556__a548e521-6c2b-4bbc-aa50-22d5639f23c8-button-1": {
          "type": "button",
          "settings": {
            "button_label": "Button label",
            "button_link": "",
            "button_style_secondary": false,
            "button_label_2": "",
            "button_link_2": "",
            "button_style_secondary_2": false
          }
        }
      },
      "block_order": [
        "template--17158705250556__a548e521-6c2b-4bbc-aa50-22d5639f23c8-heading-1",
        "template--17158705250556__a548e521-6c2b-4bbc-aa50-22d5639f23c8-text-1",
        "template--17158705250556__a548e521-6c2b-4bbc-aa50-22d5639f23c8-button-1"
      ],
      "settings": {
        "desktop_content_position": "center",
        "content_alignment": "center",
        "color_scheme": "",
        "full_width": true,
        "padding_top": 40,
        "padding_bottom": 52
      }
    },
    "main": {
      "type": "main-page",
      "settings": {
        "background_img": "shopify:\/\/shop_images\/TheBetter_OurStroy.jpg",
        "background_img_2": "shopify:\/\/shop_images\/TheBetter_OurStroy.jpg",
        "padding_top": 36,
        "padding_bottom": 36
      }
    }
  },
  "order": [
    "a548e521-6c2b-4bbc-aa50-22d5639f23c8",
    "main"
  ]
}
